testcontainers/opensearch/__init__.py
tests/test_opensearch.py
testcontainers_opensearch-0.0.1rc1.dist-info/METADATA
testcontainers_opensearch-0.0.1rc1.dist-info/WHEEL
testcontainers_opensearch-0.0.1rc1.dist-info/top_level.txt
testcontainers_opensearch-0.0.1rc1.dist-info/RECORD
